reverie_sdk/__init__.py
reverie_sdk/base.py
reverie_sdk/cli.py
reverie_sdk/services/__init__.py
reverie_sdk/services/asr.py
reverie_sdk/services/nlu.py
reverie_sdk/services/nmt.py
reverie_sdk/services/t13n.py
reverie_sdk/services/tts.py
reverie_sdk/utils/__init__.py
reverie_sdk/utils/audio_utils.py
reverie_sdk/utils/chunker.py
reverie_sdk/utils/formatters.py
reverie_sdk/utils/getters.py
reverie_sdk/utils/threadsafe_generators.py
reverie_sdk-0.1.4.dist-info/METADATA
reverie_sdk-0.1.4.dist-info/WHEEL
reverie_sdk-0.1.4.dist-info/top_level.txt
reverie_sdk-0.1.4.dist-info/RECORD
