Metadata-Version: 2.4
Name: reverie_sdk
Version: 0.1.4
Summary: Reverie Language Technologies SDK
Author: Rohnak Agarwal
Author-email: rohnak.agarwal@reverieinc.com
Classifier: Development Status :: 4 - Beta
Classifier: Intended Audience :: Developers
Classifier: Programming Language :: Python :: 3.10
Classifier: Topic :: Multimedia :: Sound/Audio :: Speech
Requires-Python: >=3.7,<3.13
Provides-Extra: py37
Requires-Dist: build==1.1.1; extra == "py37"
Requires-Dist: dotenv==0.9.9; extra == "py37"
Requires-Dist: ffmpeg==1.4; extra == "py37"
Requires-Dist: pandas==1.3.5; extra == "py37"
Requires-Dist: pip-chill==1.0.3; extra == "py37"
Requires-Dist: pydub==0.25.1; extra == "py37"
Requires-Dist: pyopenssl==25.0.0; extra == "py37"
Requires-Dist: soundfile==0.13.1; extra == "py37"
Requires-Dist: virtualenv==20.26.6; extra == "py37"
Requires-Dist: requests==2.31.0; extra == "py37"
Requires-Dist: websocket-client==1.6.1; extra == "py37"
Requires-Dist: websockets==11.0.3; extra == "py37"
Provides-Extra: py37-all
Requires-Dist: build==1.1.1; extra == "py37-all"
Requires-Dist: dotenv==0.9.9; extra == "py37-all"
Requires-Dist: requests==2.31.0; extra == "py37-all"
Requires-Dist: ffmpeg==1.4; extra == "py37-all"
Requires-Dist: pandas==1.3.5; extra == "py37-all"
Requires-Dist: pip-chill==1.0.3; extra == "py37-all"
Requires-Dist: pydub==0.25.1; extra == "py37-all"
Requires-Dist: pyopenssl==25.0.0; extra == "py37-all"
Requires-Dist: soundfile==0.13.1; extra == "py37-all"
Requires-Dist: stream2sentence==0.2.5; extra == "py37-all"
Requires-Dist: virtualenv==20.26.6; extra == "py37-all"
Requires-Dist: websocket-client==1.6.1; extra == "py37-all"
Requires-Dist: websockets==11.0.3; extra == "py37-all"
Provides-Extra: py38
Requires-Dist: requests==2.31.0; extra == "py38"
Requires-Dist: build==1.2.2.post1; extra == "py38"
Requires-Dist: colorlog==6.9.0; extra == "py38"
Requires-Dist: dotenv==0.9.9; extra == "py38"
Requires-Dist: ffmpeg==1.4; extra == "py38"
Requires-Dist: pandas==2.0.3; extra == "py38"
Requires-Dist: pip-chill==1.0.3; extra == "py38"
Requires-Dist: pydub==0.25.1; extra == "py38"
Requires-Dist: pyopenssl==25.0.0; extra == "py38"
Requires-Dist: soundfile==0.13.1; extra == "py38"
Requires-Dist: virtualenv==20.29.3; extra == "py38"
Requires-Dist: websocket-client==1.8.0; extra == "py38"
Requires-Dist: websockets==13.1; extra == "py38"
Provides-Extra: py38-all
Requires-Dist: build==1.2.2.post1; extra == "py38-all"
Requires-Dist: colorlog==6.9.0; extra == "py38-all"
Requires-Dist: dotenv==0.9.9; extra == "py38-all"
Requires-Dist: ffmpeg==1.4; extra == "py38-all"
Requires-Dist: pandas==2.0.3; extra == "py38-all"
Requires-Dist: pip-chill==1.0.3; extra == "py38-all"
Requires-Dist: requests==2.31.0; extra == "py38-all"
Requires-Dist: pydub==0.25.1; extra == "py38-all"
Requires-Dist: pyopenssl==25.0.0; extra == "py38-all"
Requires-Dist: soundfile==0.13.1; extra == "py38-all"
Requires-Dist: stream2sentence==0.2.6; extra == "py38-all"
Requires-Dist: virtualenv==20.29.3; extra == "py38-all"
Requires-Dist: websocket-client==1.8.0; extra == "py38-all"
Requires-Dist: websockets==13.1; extra == "py38-all"
Provides-Extra: py39
Requires-Dist: requests==2.31.0; extra == "py39"
Requires-Dist: build==1.2.2.post1; extra == "py39"
Requires-Dist: colorlog==6.9.0; extra == "py39"
Requires-Dist: dotenv==0.9.9; extra == "py39"
Requires-Dist: ffmpeg==1.4; extra == "py39"
Requires-Dist: pandas==2.2.3; extra == "py39"
Requires-Dist: pip-chill==1.0.3; extra == "py39"
Requires-Dist: pydub==0.25.1; extra == "py39"
Requires-Dist: pyopenssl==25.0.0; extra == "py39"
Requires-Dist: soundfile==0.13.1; extra == "py39"
Requires-Dist: virtualenv==20.29.3; extra == "py39"
Requires-Dist: websocket-client==1.8.0; extra == "py39"
Requires-Dist: websockets==15.0.1; extra == "py39"
Provides-Extra: py39-all
Requires-Dist: requests==2.31.0; extra == "py39-all"
Requires-Dist: build==1.2.2.post1; extra == "py39-all"
Requires-Dist: colorlog==6.9.0; extra == "py39-all"
Requires-Dist: dotenv==0.9.9; extra == "py39-all"
Requires-Dist: ffmpeg==1.4; extra == "py39-all"
Requires-Dist: pandas==2.2.3; extra == "py39-all"
Requires-Dist: pip-chill==1.0.3; extra == "py39-all"
Requires-Dist: pydub==0.25.1; extra == "py39-all"
Requires-Dist: pyopenssl==25.0.0; extra == "py39-all"
Requires-Dist: soundfile==0.13.1; extra == "py39-all"
Requires-Dist: stream2sentence==0.2.6; extra == "py39-all"
Requires-Dist: virtualenv==20.29.3; extra == "py39-all"
Requires-Dist: websocket-client==1.8.0; extra == "py39-all"
Requires-Dist: websockets==15.0.1; extra == "py39-all"
Provides-Extra: py310
Requires-Dist: requests==2.31.0; extra == "py310"
Requires-Dist: build==1.2.2.post1; extra == "py310"
Requires-Dist: colorlog==6.9.0; extra == "py310"
Requires-Dist: dotenv==0.9.9; extra == "py310"
Requires-Dist: ffmpeg==1.4; extra == "py310"
Requires-Dist: pandas==2.2.3; extra == "py310"
Requires-Dist: pip-chill==1.0.3; extra == "py310"
Requires-Dist: pydub==0.25.1; extra == "py310"
Requires-Dist: pyopenssl==25.0.0; extra == "py310"
Requires-Dist: soundfile==0.13.1; extra == "py310"
Requires-Dist: virtualenv==20.29.3; extra == "py310"
Requires-Dist: websocket-client==1.8.0; extra == "py310"
Requires-Dist: websockets==15.0.1; extra == "py310"
Provides-Extra: py310-all
Requires-Dist: requests==2.31.0; extra == "py310-all"
Requires-Dist: build==1.2.2.post1; extra == "py310-all"
Requires-Dist: colorlog==6.9.0; extra == "py310-all"
Requires-Dist: dotenv==0.9.9; extra == "py310-all"
Requires-Dist: ffmpeg==1.4; extra == "py310-all"
Requires-Dist: pandas==2.2.3; extra == "py310-all"
Requires-Dist: pip-chill==1.0.3; extra == "py310-all"
Requires-Dist: pydub==0.25.1; extra == "py310-all"
Requires-Dist: pyopenssl==25.0.0; extra == "py310-all"
Requires-Dist: soundfile==0.13.1; extra == "py310-all"
Requires-Dist: stream2sentence==0.3.0; extra == "py310-all"
Requires-Dist: virtualenv==20.29.3; extra == "py310-all"
Requires-Dist: websocket-client==1.8.0; extra == "py310-all"
Requires-Dist: websockets==15.0.1; extra == "py310-all"
Provides-Extra: py311
Requires-Dist: requests==2.31.0; extra == "py311"
Requires-Dist: build==1.2.2.post1; extra == "py311"
Requires-Dist: colorlog==6.9.0; extra == "py311"
Requires-Dist: dotenv==0.9.9; extra == "py311"
Requires-Dist: ffmpeg==1.4; extra == "py311"
Requires-Dist: pandas==2.2.3; extra == "py311"
Requires-Dist: pip-chill==1.0.3; extra == "py311"
Requires-Dist: pydub==0.25.1; extra == "py311"
Requires-Dist: pyopenssl==25.0.0; extra == "py311"
Requires-Dist: soundfile==0.13.1; extra == "py311"
Requires-Dist: virtualenv==20.29.3; extra == "py311"
Requires-Dist: websocket-client==1.8.0; extra == "py311"
Requires-Dist: websockets==15.0.1; extra == "py311"
Provides-Extra: py311-all
Requires-Dist: requests==2.31.0; extra == "py311-all"
Requires-Dist: build==1.2.2.post1; extra == "py311-all"
Requires-Dist: colorlog==6.9.0; extra == "py311-all"
Requires-Dist: dotenv==0.9.9; extra == "py311-all"
Requires-Dist: ffmpeg==1.4; extra == "py311-all"
Requires-Dist: pandas==2.2.3; extra == "py311-all"
Requires-Dist: pip-chill==1.0.3; extra == "py311-all"
Requires-Dist: pydub==0.25.1; extra == "py311-all"
Requires-Dist: pyopenssl==25.0.0; extra == "py311-all"
Requires-Dist: soundfile==0.13.1; extra == "py311-all"
Requires-Dist: stream2sentence==0.3.0; extra == "py311-all"
Requires-Dist: virtualenv==20.29.3; extra == "py311-all"
Requires-Dist: websocket-client==1.8.0; extra == "py311-all"
Requires-Dist: websockets==15.0.1; extra == "py311-all"
Provides-Extra: py312
Requires-Dist: build==1.2.2.post1; extra == "py312"
Requires-Dist: dotenv==0.9.9; extra == "py312"
Requires-Dist: ffmpeg==1.4; extra == "py312"
Requires-Dist: pandas==2.2.3; extra == "py312"
Requires-Dist: pip-chill==1.0.3; extra == "py312"
Requires-Dist: pydub==0.25.1; extra == "py312"
Requires-Dist: pyopenssl==25.0.0; extra == "py312"
Requires-Dist: soundfile==0.13.1; extra == "py312"
Requires-Dist: virtualenv==20.29.3; extra == "py312"
Requires-Dist: websocket-client==1.8.0; extra == "py312"
Requires-Dist: websockets==15.0.1; extra == "py312"
Requires-Dist: requests==2.31.0; extra == "py312"
Provides-Extra: py312-all
Requires-Dist: requests==2.31.0; extra == "py312-all"
Requires-Dist: build==1.2.2.post1; extra == "py312-all"
Requires-Dist: dotenv==0.9.9; extra == "py312-all"
Requires-Dist: ffmpeg==1.4; extra == "py312-all"
Requires-Dist: pandas==2.2.3; extra == "py312-all"
Requires-Dist: pip-chill==1.0.3; extra == "py312-all"
Requires-Dist: pydub==0.25.1; extra == "py312-all"
Requires-Dist: pyopenssl==25.0.0; extra == "py312-all"
Requires-Dist: soundfile==0.13.1; extra == "py312-all"
Requires-Dist: stream2sentence==0.3.0; extra == "py312-all"
Requires-Dist: virtualenv==20.29.3; extra == "py312-all"
Requires-Dist: websocket-client==1.8.0; extra == "py312-all"
Requires-Dist: websockets==15.0.1; extra == "py312-all"
Dynamic: author
Dynamic: author-email
Dynamic: classifier
Dynamic: description
Dynamic: description-content-type
Dynamic: provides-extra
Dynamic: requires-python
Dynamic: summary
